sc_gallery-0.0.15.dist-info/licenses/LICENSE
scgallery/__init__.py
scgallery/_version.py
scgallery/design.py
scgallery/gallery.py
scgallery/rules.py
scgallery/apps/sc_gallery.py
scgallery/checklists/asicflow_rules.py
scgallery/checklists/asicflow_template.json
scgallery/designs/__init__.py
scgallery/designs/aes/aes.py
scgallery/designs/aes/constraints/asap7sc7p5t_rvt.sdc
scgallery/designs/aes/constraints/gf180mcu_fd_sc_mcu7t5v0.sdc
scgallery/designs/aes/constraints/gf180mcu_fd_sc_mcu9t5v0.sdc
scgallery/designs/aes/constraints/nangate45.sdc
scgallery/designs/aes/constraints/sg13g2_stdcell.sdc
scgallery/designs/aes/constraints/sky130hd.sdc
scgallery/designs/aes/src/LICENSE
scgallery/designs/aes/src/README.md
scgallery/designs/aes/src/aes_cipher_top.v
scgallery/designs/aes/src/aes_inv_cipher_top.v
scgallery/designs/aes/src/aes_inv_sbox.v
scgallery/designs/aes/src/aes_key_expand_128.v
scgallery/designs/aes/src/aes_rcon.v
scgallery/designs/aes/src/aes_sbox.v
scgallery/designs/aes/src/timescale.v
scgallery/designs/black_parrot/black_parrot.py
scgallery/designs/black_parrot/constraints/asap7sc7p5t_rvt.sdc
scgallery/designs/black_parrot/constraints/gf180mcu_fd_sc_mcu7t5v0.sdc
scgallery/designs/black_parrot/constraints/gf180mcu_fd_sc_mcu9t5v0.sdc
scgallery/designs/black_parrot/constraints/nangate45.sdc
scgallery/designs/black_parrot/constraints/sg13g2_stdcell.sdc
scgallery/designs/black_parrot/constraints/sky130hd.sdc
scgallery/designs/black_parrot/extra/lambda.v
scgallery/designs/black_parrot/src/LICENSE
scgallery/designs/black_parrot/src/README.md
scgallery/designs/black_parrot/src/pickled.v
scgallery/designs/blinky/blinky.py
scgallery/designs/blinky/constraints/asap7sc7p5t_rvt.sdc
scgallery/designs/blinky/constraints/gf180mcu_fd_sc_mcu7t5v0.sdc
scgallery/designs/blinky/constraints/gf180mcu_fd_sc_mcu9t5v0.sdc
scgallery/designs/blinky/constraints/nangate45.sdc
scgallery/designs/blinky/constraints/sg13g2_stdcell.sdc
scgallery/designs/blinky/constraints/sky130hd.sdc
scgallery/designs/caliptra/__init__.py
sc_gallery-0.0.15.dist-info/METADATA
sc_gallery-0.0.15.dist-info/WHEEL
sc_gallery-0.0.15.dist-info/entry_points.txt
sc_gallery-0.0.15.dist-info/top_level.txt
sc_gallery-0.0.15.dist-info/RECORD
