Metadata-Version: 2.4
Name: sc-gallery
Version: 0.0.15
Summary: Design gallery for SiliconCompiler
Author-email: Peter Gadfort <gadfort@zeroasic.com>
License:                                  Apache License
Project-URL: Homepage, https://github.com/siliconcompiler/scgallery
Project-URL: Bug Tracker, https://github.com/siliconcompiler/scgallery/issues
Requires-Python: >=3.9
License-File: LICENSE
Requires-Dist: siliconcompiler>=0.35.0
Requires-Dist: lambdapdk>=0.2.0
Requires-Dist: lambdalib>=0.4.0
Provides-Extra: dev
Requires-Dist: pytest==8.4.2; extra == "dev"
Requires-Dist: pytest-xdist==3.8.0; extra == "dev"
Requires-Dist: pytest-cov==7.0.0; extra == "dev"
Provides-Extra: lint
Requires-Dist: flake8==7.3.0; extra == "lint"
Requires-Dist: tclint==0.6.1; extra == "lint"
Requires-Dist: codespell==2.4.1; extra == "lint"
Provides-Extra: docs
Requires-Dist: sphinx==8.2.3; extra == "docs"
Requires-Dist: sphinx-rtd-theme==3.0.2; extra == "docs"
Dynamic: license-file
